back_chat/__init__.py
back_chat/configuration.py
back_chat/define_api.py
back_chat/descriptors/__init__.py
back_chat/descriptors/message.py
back_chat/exceptions/__init__.py
back_chat/exceptions/error_response.py
back_chat/middleware/__init__.py
back_chat/middleware/auth.py
back_chat/middleware/auth_websocket.py
back_chat/models/__init__.py
back_chat/models/orm.py
back_chat/models/schemas.py
back_chat/routes/__init__.py
back_chat/routes/api_routes.py
back_chat/routes/streaming_routes.py
back_chat/routes/v1_routes.py
back_chat/services/__init__.py
back_chat/services/connection_manager.py
back_chat/services/rabbitmq_manager.py
back_chat/utils/__init__.py
back_chat/utils/functions.py
back_chat/utils/logger_api.py
back_chat-1.1.5.dist-info/licenses/LICENSE
back_chat-1.1.5.dist-info/METADATA
back_chat-1.1.5.dist-info/WHEEL
back_chat-1.1.5.dist-info/top_level.txt
back_chat-1.1.5.dist-info/RECORD
