Metadata-Version: 2.4
Name: back_chat
Version: 1.1.5
Home-page: https://github.com/AbelGRubio/backend-chat.git
Author: agrubio
Author-email: contact@agrubio.dev
Keywords: development,setup,setuptools
Classifier: Programming Language :: Python :: 3
Classifier: License :: OSI Approved :: MIT License
Classifier: Operating System :: OS Independent
Requires-Python: >=3.12
License-File: LICENSE
Requires-Dist: aio_pika==9.5.5
Requires-Dist: fastapi==0.116.1
Requires-Dist: python-keycloak==5.7.0
Requires-Dist: python-multipart==0.0.20
Requires-Dist: peewee==3.18.2
Requires-Dist: uvicorn==0.35.0
Requires-Dist: colorama==0.4.6
Dynamic: author
Dynamic: author-email
Dynamic: classifier
Dynamic: description
Dynamic: description-content-type
Dynamic: home-page
Dynamic: keywords
Dynamic: license-file
Dynamic: requires-dist
Dynamic: requires-python
